sqla_filters/nodes/base/__init__.py
sqla_filters/nodes/base/base.py
sqla_filters/nodes/logical/__init__.py
sqla_filters/nodes/logical/logical.py
sqla_filters/nodes/operational/__init__.py
sqla_filters/nodes/operational/operational.py
sqla_filters/parser/base/__init__.py
sqla_filters/parser/base/base_sqla_parser.py
sqla_filters/tree/__init__.py
sqla_filters/tree/tree.py
sqla_filters-0.0.2.dist-info/METADATA
sqla_filters-0.0.2.dist-info/RECORD
sqla_filters-0.0.2.dist-info/WHEEL
sqla_filters-0.0.2.dist-info/top_level.txt
