Metadata-Version: 2.1
Name: sqla-filters
Version: 0.0.2
Summary: Library to help developers to create filter for the sqlachemy orm.
Home-page: https://github.com/MarcAureleCoste/sqla-filters
Author: Marc-Aurele Coste
License: MIT
Platform: UNKNOWN
Classifier: License :: OSI Approved :: MIT License
Classifier: Operating System :: OS Independent
Classifier: Programming Language :: Python
Classifier: Programming Language :: Python :: 3
Classifier: Programming Language :: Python :: 3.6
Classifier: Programming Language :: Python :: 3.7
Classifier: Programming Language :: Python :: 3 :: Only
Classifier: Topic :: Software Development :: Libraries :: Python Modules
Provides-Extra: dev
Requires-Dist: SQLAlchemy (==1.2.10)
Provides-Extra: dev
Requires-Dist: pylint; extra == 'dev'
Requires-Dist: pep8; extra == 'dev'
Requires-Dist: autopep8; extra == 'dev'
Requires-Dist: ipython; extra == 'dev'
Requires-Dist: mypy; extra == 'dev'
Requires-Dist: pytest; extra == 'dev'
Requires-Dist: rope; extra == 'dev'
Requires-Dist: sphinx; extra == 'dev'
